bookit_df/__init__.py
bookit_df/bookit.py
bookit_df/config.py
bookit_df/stats.py
bookit_df/variable.py
bookit_df/renderers/__init__.py
bookit_df/renderers/pdf.py
bookit_df-0.1.0.dist-info/licenses/LICENSE
bookit_df-0.1.0.dist-info/METADATA
bookit_df-0.1.0.dist-info/WHEEL
bookit_df-0.1.0.dist-info/top_level.txt
bookit_df-0.1.0.dist-info/RECORD
